geo3dfeatures/__init__.py
geo3dfeatures/classification.py
geo3dfeatures/extract.py
geo3dfeatures/features.py
geo3dfeatures/fixtures.py
geo3dfeatures/io.py
geo3dfeatures/postprocess.py
geo3dfeatures/tools/__init__.py
geo3dfeatures/tools/__main__.py
geo3dfeatures/tools/featurize.py
geo3dfeatures/tools/index.py
geo3dfeatures/tools/info.py
geo3dfeatures/tools/kmean.py
geo3dfeatures/tools/predict.py
geo3dfeatures/tools/profiling.py
geo3dfeatures/tools/sample.py
geo3dfeatures/tools/train.py
geo3dfeatures-0.4.0.post2.dist-info/entry_points.txt
geo3dfeatures-0.4.0.post2.dist-info/LICENSE
geo3dfeatures-0.4.0.post2.dist-info/WHEEL
geo3dfeatures-0.4.0.post2.dist-info/METADATA
geo3dfeatures-0.4.0.post2.dist-info/RECORD
