Metadata-Version: 2.1
Name: geo3dfeatures
Version: 0.4.0.post2
Summary: Extract geometry features from 3D point clouds
Home-page: https://github.com/oslandia/geo3dfeatures
License: BSD-3-Clause
Author: Damien Garaud
Author-email: damien.garaud@oslandia.com
Requires-Python: >=3.7,<4.0
Classifier: Development Status :: 4 - Beta
Classifier: Environment :: Console
Classifier: Intended Audience :: Developers
Classifier: Intended Audience :: Science/Research
Classifier: License :: OSI Approved :: BSD License
Classifier: Natural Language :: English
Classifier: Programming Language :: Python :: 3
Classifier: Programming Language :: Python :: 3 :: Only
Classifier: Programming Language :: Python :: 3.7
Classifier: Programming Language :: Python :: 3.8
Classifier: Topic :: Scientific/Engineering
Classifier: Topic :: Scientific/Engineering :: Artificial Intelligence
Classifier: Topic :: Scientific/Engineering :: Information Analysis
Classifier: Topic :: Software Development :: Libraries
Requires-Dist: daiquiri (>=1.5.0,<2.0.0)
Requires-Dist: dask (>=0.20.2,<0.21.0)
Requires-Dist: laspy (>=1.5.1,<2.0.0)
Requires-Dist: numpy (>=1.15,<2.0)
Requires-Dist: pandas (>=0.23.4,<0.24.0)
Requires-Dist: plotly (>=4.1,<5.0)
Requires-Dist: plyfile (>=0.7.0,<0.8.0)
Requires-Dist: scikit-learn (>=0.21,<0.22)
Requires-Dist: scipy (>=1.2,<2.0)
Requires-Dist: seaborn (>=0.9.0,<0.10.0)
Requires-Dist: tables (>=3.5,<4.0)
Requires-Dist: tqdm (>=4.31.1,<5.0.0)
Project-URL: Repository, https://github.com/oslandia/geo3dfeatures
